{
  "name": "SilkCircuit",
  "background": "#0A0A0F",
  "foreground": "#E0E0E0",
  "black": "#0A0A0F",
  "red": "#FF79C6",
  "green": "#50FA7B",
  "yellow": "#F1FA8C",
  "blue": "#BD93F9",
  "purple": "#E135FF",
  "cyan": "#80FFEA",
  "white": "#E0E0E0",
  "brightBlack": "#6272A4",
  "brightRed": "#FF5555",
  "brightGreen": "#50FA7B",
  "brightYellow": "#F1FA8C",
  "brightBlue": "#BD93F9",
  "brightPurple": "#FF79C6",
  "brightCyan": "#5FFFFF",
  "brightWhite": "#FFFFFF",
  "cursorColor": "#E135FF",
  "selectionBackground": "#44475A"
}
